nestipy_decorator/__init__.py
nestipy_decorator/method.py
nestipy_decorator-0.1.3.dist-info/METADATA
nestipy_decorator-0.1.3.dist-info/WHEEL
nestipy_decorator-0.1.3.dist-info/RECORD
