Metadata-Version: 2.1
Name: nestipy-decorator
Version: 0.1.3
Summary: 
Author: tsiresymila
Author-email: tsiresymila@gmail.com
Requires-Python: >=3.10,<4.0
Classifier: Programming Language :: Python :: 3
Classifier: Programming Language :: Python :: 3.10
Classifier: Programming Language :: Python :: 3.11
Classifier: Programming Language :: Python :: 3.12
Requires-Dist: nestipy-ioc (>=0.1.10,<0.2.0)
Requires-Dist: nestipy-metadata (>=0.1.0,<0.2.0)
